simple_comet/__init__.py
simple_comet/channel.py
simple_comet/client.py
simple_comet/client_channel.py
simple_comet/comet_server.py
simple_comet/config.py
simple_comet/connection.py
simple_comet/held_connection_channel.py
simple_comet/simple_comet.py
simple_comet-0.5.data/scripts/simple_comet
simple_comet-0.5.dist-info/LICENSE.txt
simple_comet-0.5.dist-info/METADATA
simple_comet-0.5.dist-info/WHEEL
simple_comet-0.5.dist-info/top_level.txt
simple_comet-0.5.dist-info/RECORD
